phishermon/__init__.py
phishermon/action.py
phishermon/commandline.py
phishermon/constants.py
phishermon/mitigations.py
phishermon/phishermon.py
phishermon/sysmon_helper.py
phishermon/utils.py
phishermon-0.1.13.dist-info/METADATA
phishermon-0.1.13.dist-info/RECORD
phishermon-0.1.13.dist-info/WHEEL
phishermon-0.1.13.dist-info/entry_points.txt
phishermon-0.1.13.dist-info/top_level.txt
